energyplus_regressions/__init__.py
energyplus_regressions/__main__.py
energyplus_regressions/configure.py
energyplus_regressions/energyplus.py
energyplus_regressions/ep_platform.py
energyplus_regressions/epw_map.py
energyplus_regressions/runner.py
energyplus_regressions/runtests.py
energyplus_regressions/structures.py
energyplus_regressions/tk_window.py
energyplus_regressions/builds/__init__.py
energyplus_regressions/builds/base.py
energyplus_regressions/builds/install.py
energyplus_regressions/builds/makefile.py
energyplus_regressions/builds/visualstudio.py
energyplus_regressions/diffs/__init__.py
energyplus_regressions/diffs/ci_compare_script.py
energyplus_regressions/diffs/math_diff.config
energyplus_regressions/diffs/math_diff.py
energyplus_regressions/diffs/mycsv.py
energyplus_regressions/diffs/table_diff.py
energyplus_regressions/diffs/thresh_dict.py
energyplus_regressions/icons/icon.icns
energyplus_regressions/icons/icon.ico
energyplus_regressions/icons/icon.png
energyplus_regressions-2.1.6.dist-info/licenses/LICENSE
energyplus_regressions-2.1.6.dist-info/METADATA
energyplus_regressions-2.1.6.dist-info/WHEEL
energyplus_regressions-2.1.6.dist-info/entry_points.txt
energyplus_regressions-2.1.6.dist-info/top_level.txt
energyplus_regressions-2.1.6.dist-info/RECORD
