Metadata-Version: 2.4
Name: energyplus_regressions
Version: 2.1.6
Summary: A Python 3 library for evaluating regressions between EnergyPlus builds.
Home-page: https://github.com/NREL/EnergyPlusRegressionTool
Author: Edwin Lee, for NREL, for United States Department of Energy
License: ModifiedBSD
Keywords: energyplus_launch,ep_launch,EnergyPlus,eplus,Energy+,Building Simulation,Whole Building Energy Simulation,Heat Transfer,HVAC,Modeling
Platform: Linux (Tested on Ubuntu)
Platform: MacOSX
Platform: Windows
Classifier: Development Status :: 4 - Beta
Classifier: Intended Audience :: Science/Research
Classifier: Intended Audience :: Developers
Classifier: Natural Language :: English
Classifier: Operating System :: OS Independent
Classifier: Programming Language :: Python :: 3 :: Only
Classifier: Topic :: Scientific/Engineering
Classifier: Topic :: Scientific/Engineering :: Physics
Classifier: Topic :: Utilities
Requires-Python: >=3.9
License-File: LICENSE
Requires-Dist: PyPubSub
Requires-Dist: beautifulsoup4==4.12.3
Requires-Dist: PLAN-Tools>=0.5
Dynamic: author
Dynamic: classifier
Dynamic: description
Dynamic: description-content-type
Dynamic: home-page
Dynamic: keywords
Dynamic: license
Dynamic: license-file
Dynamic: platform
Dynamic: requires-dist
Dynamic: requires-python
Dynamic: summary
